setup.py
weixin_sdk/__init__.py
weixin_sdk/pay.py
weixin_sdk/public.py
weixin_sdk/utils.py
weixin_sdk.egg-info/PKG-INFO
weixin_sdk.egg-info/SOURCES.txt
weixin_sdk.egg-info/dependency_links.txt
weixin_sdk.egg-info/pbr.json
weixin_sdk.egg-info/requires.txt
weixin_sdk.egg-info/top_level.txt
weixin_sdk/crypt/Sample.py
weixin_sdk/crypt/WXBizMsgCrypt.py
weixin_sdk/crypt/__init__.py
weixin_sdk/crypt/ierror.py