Metadata-Version: 1.0
Name: weixin-sdk
Version: 1.0.5
Summary: wechat python sdk
Home-page: https://github.com/xfan001/weixin-sdk
Author: xfan001
Author-email: lifan121@gmail.com
License: UNKNOWN
Keywords: weixin wx wechat sdk
Platform: UNKNOWN
